MANIFEST.in
README.txt
setup.cfg
setup.py
src/buildout/__init__.py
src/buildout.locallib.egg-info/PKG-INFO
src/buildout.locallib.egg-info/SOURCES.txt
src/buildout.locallib.egg-info/dependency_links.txt
src/buildout.locallib.egg-info/entry_points.txt
src/buildout.locallib.egg-info/namespace_packages.txt
src/buildout.locallib.egg-info/top_level.txt
src/buildout.locallib.egg-info/zip-safe
src/buildout/locallib/__init__.py
src/buildout/locallib/extension.py