Metadata-Version: 1.0
Name: buildout.locallib
Version: 0.3.1
Summary: buildout.locallib use egg-packages installed on site-packages folder.
Home-page: http://bitbucket.org/shimizukawa/buildout.locallib/
Author: Takayuki SHIMIZUKAWA
Author-email: shimizukawa at gmail.com
License: PSL
Keywords: zc.buildout
Platform: UNKNOWN
Classifier: Development Status :: 4 - Beta
Classifier: Intended Audience :: Developers
Classifier: License :: OSI Approved :: Python Software Foundation License
Classifier: Programming Language :: Python
Classifier: Topic :: Software Development :: Build Tools
Classifier: Topic :: Software Development :: Libraries :: Python Modules
